{
  "id": "article-023",
  "article_no": "23",
  "legal_basis": "§23",
  "title": "第 23 條",
  "heading_level": 3,
  "source_file": "rules/法規/第2編-消防設計.md",
  "hierarchy": [
    "第二編 消防設計"
  ],
  "markdown": "下列場所應設置標示設備：\n- 一、供第十二條第一款、第二款第十二目、第五款第一目、第三目使用之場所，或地下層、無開口樓層、十一層以上之樓層供同條其他各款目所列場所使用，應設置出口標示燈。\n- 二、供第十二條第一款、第二款第十二目、第五款第一目、第三目使用之場所，或地下層、無開口樓層、十一層以上之樓層供同條其他各款目所列場所使用，應設置避難方向指示燈。\n- 三、戲院、電影院、歌廳、集會堂及類似場所，應設置觀眾席引導燈。\n- 四、各類場所均應設置避難指標。但設有避難方向指示燈或出口標示燈時，在其有效範圍內，得免設置避難指標。",
  "snippet": "下列場所應設置標示設備： - 一、供第十二條第一款、第二款第十二目、第五款第一目、第三目使用之場所，或地下層、無開口樓層、十一層以上之樓層供同條其他各款目所列場所使用，應設置出口標示燈。 - 二、供第十二條第一款、第二款第十二目、第五款第一目、第三目使用之場所，或地下層、無開口樓層、十一層以上之樓層供同條其他各款目所列場所使用，應設置避難方向指示燈。 - …",
  "equipment_tags": [
    "標示設備"
  ],
  "keywords": [
    "標示設備",
    "第二編 消防設計"
  ],
  "regulation": "各類場所消防安全設備設置標準",
  "regulation_version": "民國 113 年 04 月 24 日",
  "path": "regulation_articles/article-023.json"
}
