{
  "id": "article-079",
  "article_no": "79",
  "legal_basis": "§79",
  "title": "第 79 條",
  "heading_level": 5,
  "source_file": "rules/法規/第3編-第1章-滅火設備.md",
  "hierarchy": [
    "第三編 消防安全設計",
    "第一章 滅火設備",
    "第五節 泡沫滅火設備"
  ],
  "markdown": "泡沫原液之濃度，依下列規定：\n- 一、低發泡者，合成界面活性劑泡沫原液濃度在百分之三或百分之六，水成膜泡沫原液濃度在百分之一或百分之三。\n- 二、高發泡者，合成界面活性劑泡沫原液濃度在百分之三或百分之六。",
  "snippet": "泡沫原液之濃度，依下列規定： - 一、低發泡者，合成界面活性劑泡沫原液濃度在百分之三或百分之六，水成膜泡沫原液濃度在百分之一或百分之三。 - 二、高發泡者，合成界面活性劑泡沫原液濃度在百分之三或百分之六。",
  "equipment_tags": [],
  "keywords": [
    "第一章 滅火設備",
    "第三編 消防安全設計",
    "第五節 泡沫滅火設備"
  ],
  "regulation": "各類場所消防安全設備設置標準",
  "regulation_version": "民國 113 年 04 月 24 日",
  "path": "regulation_articles/article-079.json"
}
